{
  "recentFiles": [
    {
      "basename": "Dashboard",
      "path": "Utilities/Dashboard.canvas"
    },
    {
      "basename": "Trait List",
      "path": "Utilities/Lists/Trait List.md"
    },
    {
      "basename": "Spells Database",
      "path": "Player-Facing Rules/Spells/Spells Database/Spells Database.md"
    },
    {
      "basename": "Aurora Mortum",
      "path": "Player-Facing Rules/Spells/Spells Database/Essomancy/Aurora Mortum.md"
    },
    {
      "basename": "Spell Damage by Rank Chart",
      "path": "Utilities/Design References/Spell Damage by Rank Chart.md"
    },
    {
      "basename": "Spell Template",
      "path": "Templates/Markdown Templates/Mage Templates/Spell Template.md"
    },
    {
      "basename": "Aurora Vitam",
      "path": "Player-Facing Rules/Spells/Spells Database/Essomancy/Aurora Vitam.md"
    },
    {
      "basename": "Material",
      "path": "General Rules/Traits Catalog/Material.md"
    },
    {
      "basename": "To-Do List",
      "path": "Utilities/Dashboard Notes/To-Do List.md"
    },
    {
      "basename": "Spell List-Essomancy",
      "path": "Player-Facing Rules/Spells/Spell School Registry/Artifacteomancy/Spell List-Essomancy.md"
    },
    {
      "basename": "Arcane Sphere-Artifacteomancy",
      "path": "Player-Facing Rules/Spells/Arcane Spheres Ledger/Arcane Sphere-Artifacteomancy.md"
    },
    {
      "basename": "Spell List Template",
      "path": "Templates/Markdown Templates/General Templates/Spell List Template.md"
    },
    {
      "basename": "Arcane Sphere-Technomynism",
      "path": "Player-Facing Rules/Spells/Arcane Spheres Ledger/Arcane Sphere-Technomynism.md"
    },
    {
      "basename": "Arcane Sphere Template",
      "path": "Templates/Markdown Templates/General Templates/Arcane Sphere Template.md"
    },
    {
      "basename": "Activity Inserter",
      "path": "Templates/Markdown Templates/DevHelper Templates/Inserts/Activity Inserter.md"
    },
    {
      "basename": "Related Weapons Dataview",
      "path": "Templates/Markdown Templates/DevHelper Templates/Inserts/Related Weapons Dataview.md"
    },
    {
      "basename": "Spell List-Resonancia",
      "path": "Player-Facing Rules/Spells/Spell School Registry/Technomynism/Spell List-Resonancia.md"
    },
    {
      "basename": "New Equipment Template",
      "path": "Templates/Markdown Templates/Mage Templates/New Equipment Template.md"
    },
    {
      "basename": "Spell List-Glyphiamancy",
      "path": "Player-Facing Rules/Spells/Spell School Registry/Artifacteomancy/Spell List-Glyphiamancy.md"
    },
    {
      "basename": "Simple Metal Combination Resonance",
      "path": "Player-Facing Rules/Spells/Spells Database/Resonancia/Simple Metal Combination Resonance.md"
    },
    {
      "basename": "Metal Summoning Resonance",
      "path": "Player-Facing Rules/Spells/Spells Database/Resonancia/Metal Summoning Resonance.md"
    },
    {
      "basename": "Dodge",
      "path": "Player-Facing Rules/Character Creation/Mages/Mage Skills/Defenses/Dodge.md"
    },
    {
      "basename": "Skill Template",
      "path": "Templates/Markdown Templates/Mage Templates/Skill Template.md"
    },
    {
      "basename": "Pain-Tolerance",
      "path": "Player-Facing Rules/Character Creation/Mages/Mage Skills/Defenses/Pain-Tolerance.md"
    },
    {
      "basename": "Skills Database",
      "path": "Player-Facing Rules/Character Creation/Mages/Mage Skills/Skills Database.md"
    },
    {
      "basename": "Block",
      "path": "Player-Facing Rules/Character Creation/Mages/Mage Skills/Defenses/Block.md"
    },
    {
      "basename": "Athletics",
      "path": "Player-Facing Rules/Character Creation/Mages/Mage Skills/Physical/Athletics.md"
    },
    {
      "basename": "Favor System Primer",
      "path": "General Rules/The Favor System/Favor System Primer.md"
    },
    {
      "basename": "Dice Overview",
      "path": "General Rules/The Favor System/Dice Structure/Dice Overview.md"
    },
    {
      "basename": "Trance",
      "path": "Player-Facing Rules/Character Creation/Mages/Mage Skills/General/Trance.md"
    },
    {
      "basename": "Dev Helpers",
      "path": "Utilities/Dashboard Notes/Dev Helpers.md"
    },
    {
      "basename": "README",
      "path": "README.md"
    },
    {
      "basename": "Wormik's Torrent",
      "path": "Player-Facing Rules/Spells/Spells Database/Hydrophasia/Wormik's Torrent.md"
    },
    {
      "basename": "Equipment Database",
      "path": "Player-Facing Rules/Items and Equipment/Equipment Catalog/Equipment/Equipment Database.md"
    },
    {
      "basename": "Cyber-Arm",
      "path": "Player-Facing Rules/Items and Equipment/Equipment Catalog/Equipment/Cybernetic/Cyber-Arm.md"
    },
    {
      "basename": "High-Integrity Torque Converter",
      "path": "Player-Facing Rules/Items and Equipment/Equipment Catalog/Equipment/Cybernetic/High-Integrity Torque Converter.md"
    },
    {
      "basename": "Integrated Weapon",
      "path": "Player-Facing Rules/Items and Equipment/Equipment Catalog/Equipment/Cybernetic/Integrated Weapon.md"
    },
    {
      "basename": "Conditions Database",
      "path": "General Rules/Conditions Catalog/Conditions Database.md"
    },
    {
      "basename": "Hastened",
      "path": "General Rules/Conditions Catalog/Beneficial/Hastened.md"
    },
    {
      "basename": "Regeneration",
      "path": "General Rules/Conditions Catalog/Beneficial/Regeneration.md"
    },
    {
      "basename": "Soaked",
      "path": "General Rules/Conditions Catalog/Detrimental/Soaked.md"
    },
    {
      "basename": "Bloodied",
      "path": "General Rules/Conditions Catalog/Detrimental/Bloodied.md"
    },
    {
      "basename": "Slowed",
      "path": "General Rules/Conditions Catalog/Slowed.md"
    },
    {
      "basename": "Power-Word 'Haste'",
      "path": "Player-Facing Rules/Spells/Spells Database/Runeurgy/Power-Word 'Haste'.md"
    },
    {
      "basename": "Condition Template",
      "path": "Templates/Markdown Templates/General Templates/Condition Template.md"
    },
    {
      "basename": "Unknown",
      "path": "General Rules/Conditions Catalog/Unknown.md"
    },
    {
      "basename": "Conditions List",
      "path": "Utilities/Lists/Conditions List.md"
    },
    {
      "basename": "Magical",
      "path": "General Rules/Traits Catalog/General/Magical.md"
    },
    {
      "basename": "Shifting Tides",
      "path": "Player-Facing Rules/Spells/Spells Database/Hydrophasia/Shifting Tides.md"
    },
    {
      "basename": "Hydro-Oscillation Field",
      "path": "Player-Facing Rules/Spells/Spells Database/Hydrophasia/Hydro-Oscillation Field.md"
    }
  ],
  "omittedPaths": [],
  "maxLength": null,
  "openType": "tab"
}