{"Spell-Only":{"Spell-Only":{"frontMatter":{"count":1,"lastUpdated":1712297119638}}},"Distraction":{"Distraction":{"currentFile":{"count":1,"lastUpdated":1712298417613}}},"temporary":{"temporary":{"currentFile":{"count":2,"lastUpdated":1712299163199}}},"performances":{"performances":{"currentFile":{"count":1,"lastUpdated":1712299297831}}},"specific":{"specific":{"currentFile":{"count":1,"lastUpdated":1712301958093}}},"negotiate":{"negotiate":{"currentFile":{"count":1,"lastUpdated":1712303789469}}},"Intimidation":{"Intimidation":{"internalLink":{"count":1,"lastUpdated":1712304063098}}},"Demoralize":{"Demoralize":{"currentFile":{"count":1,"lastUpdated":1712305506020}}},"mundane":{"mundane":{"currentFile":{"count":1,"lastUpdated":1712562211248}}},"artifice":{"artifice":{"currentFile":{"count":1,"lastUpdated":1712562356349}}},"Hydro-Oscillation Field":{"Hydro-Oscillation Field":{"internalLink":{"count":1,"lastUpdated":1714797565641}}}}